paunch/__init__.py
paunch/__main__.py
paunch/cmd.py
paunch/constants.py
paunch/runner.py
paunch/builder/__init__.py
paunch/builder/base.py
paunch/builder/compose1.py
paunch/builder/podman.py
paunch/tests/__init__.py
paunch/tests/base.py
paunch/tests/test_builder_base.py
paunch/tests/test_builder_compose1.py
paunch/tests/test_builder_podman.py
paunch/tests/test_paunch.py
paunch/tests/test_runner.py
paunch/tests/test_utils_common.py
paunch/tests/test_utils_systemctl.py
paunch/tests/test_utils_systemd.py
paunch/utils/__init__.py
paunch/utils/common.py
paunch/utils/systemctl.py
paunch/utils/systemd.py
paunch-7.0.4.dist-info/AUTHORS
paunch-7.0.4.dist-info/LICENSE
paunch-7.0.4.dist-info/METADATA
paunch-7.0.4.dist-info/WHEEL
paunch-7.0.4.dist-info/entry_points.txt
paunch-7.0.4.dist-info/pbr.json
paunch-7.0.4.dist-info/top_level.txt
paunch-7.0.4.dist-info/RECORD
