Metadata-Version: 2.1
Name: paunch
Version: 7.0.4
Summary: Utility to launch and manage containers using YAML based configuration data
Home-page: https://docs.openstack.org/paunch/latest/
Author: OpenStack
Author-email: openstack-discuss@lists.openstack.org
License: UNKNOWN
Platform: UNKNOWN
Classifier: Environment :: OpenStack
Classifier: Intended Audience :: Information Technology
Classifier: Intended Audience :: System Administrators
Classifier: License :: OSI Approved :: Apache Software License
Classifier: Operating System :: POSIX :: Linux
Classifier: Programming Language :: Python
Classifier: Programming Language :: Python :: Implementation :: CPython
Classifier: Programming Language :: Python :: 3 :: Only
Classifier: Programming Language :: Python :: 3
Classifier: Programming Language :: Python :: 3.6
Classifier: Programming Language :: Python :: 3.7
Requires-Python: >=3.6
Requires-Dist: cliff (>=2.6.0)
Requires-Dist: jmespath (>=0.9.0)
Requires-Dist: pbr (!=2.1.0,>=2.0.0)
Requires-Dist: psutil (>=3.2.2)
Requires-Dist: tenacity (>=3.2.1)
